basic_usage.cp312-win_amd64.pyd
minimal_test.cp312-win_amd64.pyd
mysql_connect.cp312-win_amd64.pyd
postgres_connect.cp312-win_amd64.pyd
postgres_usage.cp312-win_amd64.pyd
test_embeddings.cp312-win_amd64.pyd
test_knowledge_base.cp312-win_amd64.pyd
test_ollama.cp312-win_amd64.pyd
test_retry_mechanism.cp312-win_amd64.pyd
test_training.cp312-win_amd64.pyd
mdsmart/README.md
mdsmart/__init__.c
mdsmart/__init__.cp312-win_amd64.pyd
mdsmart/auto_fix.c
mdsmart/auto_fix.cp312-win_amd64.pyd
mdsmart/config.c
mdsmart/config.cp312-win_amd64.pyd
mdsmart/core.c
mdsmart/core.cp312-win_amd64.pyd
mdsmart/database.c
mdsmart/database.cp312-win_amd64.pyd
mdsmart/exceptions.c
mdsmart/exceptions.cp312-win_amd64.pyd
mdsmart/knowledge.c
mdsmart/knowledge.cp312-win_amd64.pyd
mdsmart/utils.c
mdsmart/utils.cp312-win_amd64.pyd
mdsmart/vector_store.c
mdsmart/vector_store.cp312-win_amd64.pyd
mdsmart/vector_store_milvus_backup.c
mdsmart/vector_store_milvus_backup.cp312-win_amd64.pyd
mdsmart-0.1.0.dist-info/licenses/LICENSE
mdsmart-0.1.0.dist-info/METADATA
mdsmart-0.1.0.dist-info/WHEEL
mdsmart-0.1.0.dist-info/top_level.txt
mdsmart-0.1.0.dist-info/RECORD
