Metadata-Version: 2.4
Name: mdsmart
Version: 0.1.0
Summary: Multi-Database Smart Query Generator - Convert natural language to SQL using AI
Author-email: Shivam Parmar <shivam.parmar@gmail.com>
License-Expression: MIT
Requires-Python: >=3.8
License-File: LICENSE
Requires-Dist: pandas>=1.3.0
Requires-Dist: requests>=2.26.0
Requires-Dist: faiss-cpu>=1.7.4
Requires-Dist: numpy>=1.21.0
Provides-Extra: gpu
Requires-Dist: faiss-gpu>=1.7.4; extra == "gpu"
Provides-Extra: postgres
Requires-Dist: psycopg2-binary>=2.9.0; extra == "postgres"
Provides-Extra: mysql
Requires-Dist: pymysql>=1.0.0; extra == "mysql"
Provides-Extra: pdf
Requires-Dist: PyPDF2>=3.0.0; extra == "pdf"
Provides-Extra: all
Requires-Dist: faiss-cpu>=1.7.4; extra == "all"
Requires-Dist: psycopg2-binary>=2.9.0; extra == "all"
Requires-Dist: pymysql>=1.0.0; extra == "all"
Requires-Dist: PyPDF2>=3.0.0; extra == "all"
Dynamic: license-file
